EasyFacesPy/__init__.py
EasyFacesPy-0.0.7.dist-info/METADATA
EasyFacesPy-0.0.7.dist-info/WHEEL
EasyFacesPy-0.0.7.dist-info/top_level.txt
EasyFacesPy-0.0.7.dist-info/RECORD
