Metadata-Version: 2.1
Name: EasyFacesPy
Version: 0.0.7
Summary: This library will help you with face recognition in photos.
Home-page: UNKNOWN
Author: Nellle
Author-email: UNKNOWN
License: UNKNOWN
Keywords: python,face,opencv
Platform: UNKNOWN
Classifier: Development Status :: 2 - Pre-Alpha
Classifier: Intended Audience :: Developers
Classifier: Programming Language :: Python :: 3
Classifier: Operating System :: Unix
Classifier: Operating System :: MacOS :: MacOS X
Classifier: Operating System :: Microsoft :: Windows
Requires-Dist: opencv-python
Requires-Dist: Pillow
